[
    {
        "id": "1161",
        "word": "diameter",
        "raw_meaning": "지름, 직경"
    },
    {
        "id": "1162",
        "word": "anecdote",
        "raw_meaning": "일화, 비화"
    },
    {
        "id": "1163",
        "word": "spatial",
        "raw_meaning": "공간의, 공간적인"
    },
    {
        "id": "1164",
        "word": "blame",
        "raw_meaning": "비난하다, ~의 탓으로 돌리다, 비난, 책망"
    },
    {
        "id": "1165",
        "word": "geology",
        "raw_meaning": "지질학"
    },
    {
        "id": "1166",
        "word": "pledge",
        "raw_meaning": "약속, 맹세, 약속하다, 맹세하다"
    },
    {
        "id": "1167",
        "word": "cost",
        "raw_meaning": "(비용이) 들다, 비용, 대가"
    },
    {
        "id": "1168",
        "word": "earn",
        "raw_meaning": "(신용·평판 등을) 얻다, (돈을) 벌다"
    },
    {
        "id": "1169",
        "word": "detect",
        "raw_meaning": "발견하다, 감지하다"
    },
    {
        "id": "1170",
        "word": "temperate",
        "raw_meaning": "(기후가) 온화한, 절제하는"
    },
    {
        "id": "1171",
        "word": "soar",
        "raw_meaning": "높이 치솟다"
    },
    {
        "id": "1172",
        "word": "mock",
        "raw_meaning": "조롱하다, 가짜의"
    },
    {
        "id": "1173",
        "word": "disclose",
        "raw_meaning": "드러내다, 폭로하다"
    },
    {
        "id": "1174",
        "word": "exhibit",
        "raw_meaning": "전시하다, 보여 주다, 전시, 전시품"
    },
    {
        "id": "1175",
        "word": "symptom",
        "raw_meaning": "증상"
    },
    {
        "id": "1176",
        "word": "invent",
        "raw_meaning": "발명하다"
    },
    {
        "id": "1177",
        "word": "awkward",
        "raw_meaning": "어색한, 서투른"
    },
    {
        "id": "1178",
        "word": "grind",
        "raw_meaning": "갈다, 빻다"
    },
    {
        "id": "1179",
        "word": "expose",
        "raw_meaning": "드러내다, (비밀을) 폭로하다, 노출시키다"
    },
    {
        "id": "1180",
        "word": "closet",
        "raw_meaning": "벽장"
    },
    {
        "id": "1181",
        "word": "damp",
        "raw_meaning": "축축한, 습기, 습한, 젖은"
    },
    {
        "id": "1182",
        "word": "script",
        "raw_meaning": "손으로 쓰기, 대본"
    },
    {
        "id": "1183",
        "word": "signify",
        "raw_meaning": "의미하다, 중요하다"
    },
    {
        "id": "1184",
        "word": "discuss",
        "raw_meaning": "토론하다"
    },
    {
        "id": "1185",
        "word": "sibling",
        "raw_meaning": "형제자매, 동기"
    },
    {
        "id": "1186",
        "word": "lay",
        "raw_meaning": "(물건을) 놓다, (알을) 낳다"
    },
    {
        "id": "1187",
        "word": "surveillance",
        "raw_meaning": "감시, 관찰"
    },
    {
        "id": "1188",
        "word": "discharge",
        "raw_meaning": "배출, 내보냄, 방전, 배출하다, 내보내다, 해고하다"
    },
    {
        "id": "1189",
        "word": "thorough",
        "raw_meaning": "철저한"
    },
    {
        "id": "1190",
        "word": "undertake",
        "raw_meaning": "수행하다, (일을) 떠맡다, 착수하다"
    },
    {
        "id": "1191",
        "word": "panel",
        "raw_meaning": "토론자단, 패널, 넓은 직사각형의 합판"
    },
    {
        "id": "1192",
        "word": "linguistic",
        "raw_meaning": "언어의, 언어학의"
    },
    {
        "id": "1193",
        "word": "flourish",
        "raw_meaning": "번영하다, 번창하다"
    },
    {
        "id": "1194",
        "word": "feed",
        "raw_meaning": "먹이를 주다, 부양하다"
    },
    {
        "id": "1195",
        "word": "sophomore",
        "raw_meaning": "(대학·고등학교의) 2학년생"
    },
    {
        "id": "1196",
        "word": "remind",
        "raw_meaning": "생각나게 하다, 상기시키다"
    },
    {
        "id": "1197",
        "word": "sole",
        "raw_meaning": "유일한"
    },
    {
        "id": "1198",
        "word": "pillar",
        "raw_meaning": "기둥"
    },
    {
        "id": "1199",
        "word": "explode",
        "raw_meaning": "폭발하다"
    },
    {
        "id": "1200",
        "word": "illusion",
        "raw_meaning": "환상, 착각"
    }
]